google_play_scraper/__init__.py
google_play_scraper/client.py
google_play_scraper/constants.py
google_play_scraper/exceptions.py
google_play_scraper/models.py
google_play_scraper/py.typed
google_play_scraper/internal/__init__.py
google_play_scraper/internal/extractor.py
google_play_scraper/internal/parser.py
google_play_scraper/internal/request.py
google_play_scraper/internal/request_constants.py
play_store_scraper_ng-0.1.5.dist-info/licenses/LICENSE
play_store_scraper_ng-0.1.5.dist-info/METADATA
play_store_scraper_ng-0.1.5.dist-info/WHEEL
play_store_scraper_ng-0.1.5.dist-info/top_level.txt
play_store_scraper_ng-0.1.5.dist-info/RECORD
