Metadata-Version: 2.4
Name: play-store-scraper-ng
Version: 0.1.5
Summary: Modern, typed Google Play Store scraper client with Pydantic models.
Author: Artem Smirnov
License: The MIT License (MIT)
Project-URL: Homepage, https://pypi.org/project/play-store-scraper-ng/
Project-URL: Source, https://github.com/RankoR/google-play-scraper
Project-URL: Issues, https://github.com/RankoR/google-play-scraper/issues
Keywords: google,play,android,scraper,apps,reviews,search
Classifier: Development Status :: 4 - Beta
Classifier: Intended Audience :: Developers
Classifier: License :: OSI Approved :: MIT License
Classifier: Programming Language :: Python
Classifier: Programming Language :: Python :: 3
Classifier: Programming Language :: Python :: 3 :: Only
Classifier: Programming Language :: Python :: 3.11
Classifier: Programming Language :: Python :: 3.12
Classifier: Programming Language :: Python :: 3.13
Classifier: Programming Language :: Python :: 3.14
Classifier: Topic :: Internet :: WWW/HTTP
Classifier: Typing :: Typed
Requires-Python: >=3.11
License-File: LICENSE
Requires-Dist: pydantic>=2.0
Requires-Dist: httpx>=0.27.0
Dynamic: license-file
